TorchEase/__init__.py
TorchEase/comparer.py
TorchEase/fuser.py
TorchEase/modelbase.py
TorchEase/test.py
TorchEase/trainer.py
TorchEase/user.py
TorchEase/utilities.py
TorchEase-0.0.26.dist-info/METADATA
TorchEase-0.0.26.dist-info/WHEEL
TorchEase-0.0.26.dist-info/top_level.txt
TorchEase-0.0.26.dist-info/RECORD
