Metadata-Version: 2.1
Name: TorchEase
Version: 0.0.26
Summary: Simplifying working with PyTorch
Author: Philipp Steigerwald
Author-email: info@b-stream.info
Keywords: torch,pytorch,early stop,trainer,tensor
Classifier: Development Status :: 1 - Planning
Classifier: Intended Audience :: Developers
Classifier: Programming Language :: Python :: 3
Classifier: Operating System :: Unix
Classifier: Operating System :: MacOS :: MacOS X
Classifier: Operating System :: Microsoft :: Windows
Requires-Dist: scikit-learn
Requires-Dist: matplotlib
Requires-Dist: pandas
Requires-Dist: torch
Requires-Dist: numpy
Requires-Dist: scipy
